[
  {
    "basicInfo": {
      "homeTeam": false
    }, 
    "stats": {
      "ftp": 75.9, 
      "blocks": 6.0, 
      "tpa": 30.0, 
      "plusMinus": -9.0, 
      "totReb": 46.0, 
      "min": "240:00", 
      "fgp": 48.4, 
      "fga": 93.0, 
      "fta": 29.0, 
      "fgm": 45.0, 
      "points": 119.0, 
      "offReb": 8.0, 
      "assists": 23.0, 
      "tpp": 23.3, 
      "defReb": 38.0, 
      "pFouls": 26.0, 
      "ftm": 22.0, 
      "tpm": 7.0, 
      "steals": 10.0, 
      "turnovers": 15.0
    }
  }, 
  {
    "basicInfo": {
      "homeTeam": true
    }, 
    "stats": {
      "ftp": 61.1, 
      "blocks": 10.0, 
      "tpa": 32.0, 
      "min": "240:00", 
      "totReb": 44.0, 
      "plusMinus": -9.0, 
      "fgp": 48.0, 
      "fta": 18.0, 
      "fgm": 48.0, 
      "tpm": 8.0, 
      "points": 115.0, 
      "offReb": 9.0, 
      "assists": 28.0, 
      "tpp": 25.0, 
      "defReb": 35.0, 
      "pFouls": 21.0, 
      "ftm": 11.0, 
      "fga": 100.0, 
      "steals": 8.0, 
      "turnovers": 10.0
    }
  }, 
  {
    "basicInfo": {
      "homeTeam": true
    }, 
    "stats": {
      "ftp": 69.2, 
      "blocks": 6.0, 
      "points": 142.0, 
      "tpa": 39.0, 
      "min": "265:00", 
      "totReb": 52.0, 
      "fgp": 51.4, 
      "fga": 107.0, 
      "fta": 26.0, 
      "fgm": 55.0, 
      "plusMinus": -1.0, 
      "offReb": 13.0, 
      "assists": 33.0, 
      "tpp": 35.9, 
      "defReb": 39.0, 
      "pFouls": 29.0, 
      "ftm": 18.0, 
      "tpm": 14.0, 
      "steals": 5.0, 
      "turnovers": 15.0
    }
  }, 
  {
    "basicInfo": {
      "homeTeam": false
    }, 
    "stats": {
      "ftp": 73.9, 
      "blocks": 5.0, 
      "tpa": 28.0, 
      "min": "240:00", 
      "totReb": 43.0, 
      "fgp": 52.0, 
      "turnovers": 8.0, 
      "fta": 23.0, 
      "fgm": 52.0, 
      "tpm": 10.0, 
      "plusMinus": 18.0, 
      "offReb": 11.0, 
      "assists": 34.0, 
      "tpp": 35.7, 
      "defReb": 32.0, 
      "pFouls": 19.0, 
      "ftm": 17.0, 
      "fga": 100.0, 
      "steals": 13.0, 
      "points": 131.0
    }
  }, 
  {
    "basicInfo": {
      "homeTeam": true
    }, 
    "stats": {
      "ftp": 82.6, 
      "blocks": 3.0, 
      "tpa": 29.0, 
      "plusMinus": 7.0, 
      "totReb": 42.0, 
      "min": "240:00", 
      "fgp": 50.0, 
      "fga": 92.0, 
      "fta": 23.0, 
      "fgm": 46.0, 
      "points": 121.0, 
      "offReb": 9.0, 
      "assists": 27.0, 
      "tpp": 34.5, 
      "defReb": 33.0, 
      "pFouls": 19.0, 
      "ftm": 19.0, 
      "tpm": 10.0, 
      "steals": 13.0, 
      "turnovers": 13.0
    }
  }, 
  {
    "basicInfo": {
      "homeTeam": false
    }, 
    "stats": {
      "ftp": 61.1, 
      "blocks": 5.0, 
      "tpa": 33.0, 
      "min": "240:00", 
      "totReb": 42.0, 
      "plusMinus": -4.0, 
      "fgp": 47.7, 
      "fta": 18.0, 
      "fgm": 41.0, 
      "tpm": 13.0, 
      "points": 106.0, 
      "offReb": 7.0, 
      "assists": 19.0, 
      "tpp": 39.4, 
      "defReb": 35.0, 
      "pFouls": 25.0, 
      "ftm": 11.0, 
      "fga": 86.0, 
      "steals": 5.0, 
      "turnovers": 17.0
    }
  }, 
  {
    "basicInfo": {
      "homeTeam": false
    }, 
    "stats": {
      "ftp": 66.7, 
      "blocks": 8.0, 
      "points": 120.0, 
      "tpa": 33.0, 
      "min": "240:00", 
      "totReb": 48.0, 
      "fgp": 47.1, 
      "fga": 104.0, 
      "fta": 15.0, 
      "fgm": 49.0, 
      "plusMinus": -4.0, 
      "offReb": 17.0, 
      "assists": 24.0, 
      "tpp": 36.4, 
      "defReb": 31.0, 
      "pFouls": 24.0, 
      "ftm": 10.0, 
      "tpm": 12.0, 
      "steals": 8.0, 
      "turnovers": 18.0
    }
  }, 
  {
    "basicInfo": {
      "homeTeam": true
    }, 
    "stats": {
      "ftp": 75.0, 
      "blocks": 6.0, 
      "tpa": 17.0, 
      "min": "240:00", 
      "totReb": 39.0, 
      "fgp": 51.2, 
      "turnovers": 20.0, 
      "fta": 24.0, 
      "fgm": 43.0, 
      "tpm": 10.0, 
      "plusMinus": 1.0, 
      "offReb": 8.0, 
      "assists": 23.0, 
      "tpp": 58.8, 
      "defReb": 31.0, 
      "pFouls": 27.0, 
      "ftm": 18.0, 
      "fga": 84.0, 
      "steals": 12.0, 
      "points": 114.0
    }
  }, 
  {
    "basicInfo": {
      "homeTeam": false
    }, 
    "stats": {
      "ftp": 64.0, 
      "blocks": 11.0, 
      "tpa": 21.0, 
      "plusMinus": 4.0, 
      "totReb": 50.0, 
      "min": "240:00", 
      "fgp": 52.3, 
      "fga": 86.0, 
      "fta": 25.0, 
      "fgm": 45.0, 
      "points": 114.0, 
      "offReb": 9.0, 
      "assists": 20.0, 
      "tpp": 38.1, 
      "defReb": 41.0, 
      "pFouls": 22.0, 
      "ftm": 16.0, 
      "tpm": 8.0, 
      "steals": 9.0, 
      "turnovers": 20.0
    }
  }, 
  {
    "basicInfo": {
      "homeTeam": true
    }, 
    "stats": {
      "ftp": 79.3, 
      "blocks": 4.0, 
      "tpa": 24.0, 
      "min": "240:00", 
      "totReb": 38.0, 
      "plusMinus": -14.0, 
      "fgp": 45.9, 
      "fta": 29.0, 
      "fgm": 39.0, 
      "tpm": 6.0, 
      "points": 107.0, 
      "offReb": 6.0, 
      "assists": 25.0, 
      "tpp": 25.0, 
      "defReb": 32.0, 
      "pFouls": 18.0, 
      "ftm": 23.0, 
      "fga": 85.0, 
      "steals": 6.0, 
      "turnovers": 16.0
    }
  }, 
  {
    "basicInfo": {
      "homeTeam": true
    }, 
    "stats": {
      "ftp": 78.6, 
      "blocks": 4.0, 
      "points": 114.0, 
      "tpa": 34.0, 
      "min": "240:00", 
      "totReb": 47.0, 
      "fgp": 48.4, 
      "fga": 91.0, 
      "fta": 14.0, 
      "fgm": 44.0, 
      "plusMinus": 4.0, 
      "offReb": 12.0, 
      "assists": 32.0, 
      "tpp": 44.1, 
      "defReb": 35.0, 
      "pFouls": 14.0, 
      "ftm": 11.0, 
      "tpm": 15.0, 
      "steals": 6.0, 
      "turnovers": 16.0
    }
  }, 
  {
    "basicInfo": {
      "homeTeam": false
    }, 
    "stats": {
      "ftp": 41.2, 
      "blocks": 3.0, 
      "tpa": 38.0, 
      "min": "240:00", 
      "totReb": 59.0, 
      "fgp": 41.4, 
      "turnovers": 14.0, 
      "fta": 17.0, 
      "fgm": 41.0, 
      "tpm": 12.0, 
      "plusMinus": 15.0, 
      "offReb": 17.0, 
      "assists": 23.0, 
      "tpp": 31.6, 
      "defReb": 42.0, 
      "pFouls": 20.0, 
      "ftm": 7.0, 
      "fga": 99.0, 
      "steals": 11.0, 
      "points": 101.0
    }
  }, 
  {
    "basicInfo": {
      "homeTeam": true
    }, 
    "stats": {
      "ftp": 62.5, 
      "blocks": 9.0, 
      "tpa": 38.0, 
      "plusMinus": 1.0, 
      "totReb": 48.0, 
      "min": "240:00", 
      "fgp": 42.4, 
      "fga": 92.0, 
      "fta": 24.0, 
      "fgm": 39.0, 
      "points": 107.0, 
      "offReb": 17.0, 
      "assists": 28.0, 
      "tpp": 36.8, 
      "defReb": 31.0, 
      "pFouls": 23.0, 
      "ftm": 15.0, 
      "tpm": 14.0, 
      "steals": 12.0, 
      "turnovers": 22.0
    }
  }, 
  {
    "basicInfo": {
      "homeTeam": true
    }, 
    "stats": {
      "ftp": 88.5, 
      "blocks": 6.0, 
      "tpa": 32.0, 
      "min": "240:00", 
      "totReb": 48.0, 
      "plusMinus": 9.0, 
      "fgp": 47.3, 
      "fta": 26.0, 
      "fgm": 44.0, 
      "tpm": 15.0, 
      "points": 126.0, 
      "offReb": 11.0, 
      "assists": 25.0, 
      "tpp": 46.9, 
      "defReb": 37.0, 
      "pFouls": 18.0, 
      "ftm": 23.0, 
      "fga": 93.0, 
      "steals": 11.0, 
      "turnovers": 13.0
    }
  }, 
  {
    "basicInfo": {
      "homeTeam": false
    }, 
    "stats": {
      "ftp": 84.0, 
      "blocks": 6.0, 
      "points": 117.0, 
      "tpa": 30.0, 
      "min": "240:00", 
      "totReb": 41.0, 
      "fgp": 47.8, 
      "fga": 90.0, 
      "fta": 25.0, 
      "fgm": 43.0, 
      "plusMinus": -13.0, 
      "offReb": 8.0, 
      "assists": 22.0, 
      "tpp": 33.3, 
      "defReb": 33.0, 
      "pFouls": 20.0, 
      "ftm": 21.0, 
      "tpm": 10.0, 
      "steals": 5.0, 
      "turnovers": 14.0
    }
  }, 
  {
    "basicInfo": {
      "homeTeam": false
    }, 
    "stats": {
      "ftp": 85.7, 
      "blocks": 5.0, 
      "tpa": 27.0, 
      "min": "240:00", 
      "totReb": 50.0, 
      "fgp": 44.2, 
      "turnovers": 9.0, 
      "fta": 21.0, 
      "fgm": 42.0, 
      "tpm": 11.0, 
      "plusMinus": 16.0, 
      "offReb": 14.0, 
      "assists": 16.0, 
      "tpp": 40.7, 
      "defReb": 36.0, 
      "pFouls": 19.0, 
      "ftm": 18.0, 
      "fga": 95.0, 
      "steals": 7.0, 
      "points": 113.0
    }
  }, 
  {
    "basicInfo": {
      "homeTeam": false
    }, 
    "stats": {
      "ftp": 71.4, 
      "blocks": 9.0, 
      "tpa": 25.0, 
      "plusMinus": 4.0, 
      "totReb": 51.0, 
      "min": "240:00", 
      "fgp": 51.3, 
      "fga": 78.0, 
      "fta": 28.0, 
      "fgm": 40.0, 
      "points": 109.0, 
      "offReb": 7.0, 
      "assists": 23.0, 
      "tpp": 36.0, 
      "defReb": 44.0, 
      "pFouls": 20.0, 
      "ftm": 20.0, 
      "tpm": 9.0, 
      "steals": 2.0, 
      "turnovers": 15.0
    }
  }, 
  {
    "basicInfo": {
      "homeTeam": true
    }, 
    "stats": {
      "ftp": 61.1, 
      "totReb": 47.0, 
      "blocks": 5.0, 
      "tpa": 23.0, 
      "plusMinus": 7.0, 
      "tpm": 7.0, 
      "min": "240:00", 
      "fgp": 45.6, 
      "fta": 18.0, 
      "fgm": 36.0, 
      "points": 90.0, 
      "offReb": 5.0, 
      "assists": 10.0, 
      "tpp": 30.4, 
      "defReb": 42.0, 
      "pFouls": 20.0, 
      "ftm": 11.0, 
      "fga": 79.0, 
      "steals": 11.0, 
      "turnovers": 23.0
    }
  }
]